tstring/__init__.py
tstring/_version.py
tstring/py.typed
tstring/template.py
tstring-0.1.2.dist-info/LICENSE.md
tstring-0.1.2.dist-info/METADATA
tstring-0.1.2.dist-info/WHEEL
tstring-0.1.2.dist-info/top_level.txt
tstring-0.1.2.dist-info/RECORD
