Metadata-Version: 2.1
Name: tstring
Version: 0.1.2
Summary: Delayed fstring-like string templates in python.
Author-email: Maxwell Levin <24307537+maxwelllevin@users.noreply.github.com>
License: BSD 3-Clause License
Keywords: string,template
Classifier: Programming Language :: Python :: 3
Requires-Python: >=3.7
License-File: LICENSE.md
